genaisys/__init__.py
genaisys/pygame/__init__.py
genaisys/pygame/snake.py
genaisys/systems/duckdb.py
genaisys-0.1.1.dist-info/LICENSE
genaisys-0.1.1.dist-info/METADATA
genaisys-0.1.1.dist-info/WHEEL
genaisys-0.1.1.dist-info/RECORD
