Metadata-Version: 2.1
Name: genaisys
Version: 0.1.1
Summary: 
Author: riaz
Author-email: riaz.2012@gmail.com
Requires-Python: >=3.11,<4.0
Classifier: Programming Language :: Python :: 3
Classifier: Programming Language :: Python :: 3.11
Classifier: Programming Language :: Python :: 3.12
Requires-Dist: duckdb (>=1.0.0,<2.0.0)
Requires-Dist: pandas (>=2.2.2,<3.0.0)
Requires-Dist: pygame (>=2.5.2,<3.0.0)
Requires-Dist: pytest (>=8.2.2,<9.0.0)
